cachebot
