Metadata-Version: 1.0
Name: django-cachebot
Version: 0.4.1
Summary: Automated caching and invalidation for the Django ORM
Home-page: http://github.com/dziegler/django-cachebot
Author: David Ziegler
Author-email: david.ziegler@gmail.com
License: BSD
Download-URL: http://github.com/dziegler/django-cachebot/archives/master
Platform: UNKNOWN
Classifier: Environment :: Web Environment
Classifier: Framework :: Django
Classifier: Intended Audience :: Developers
Classifier: License :: OSI Approved :: BSD License
Classifier: Operating System :: OS Independent
Classifier: Programming Language :: Python
Classifier: Topic :: Internet :: WWW/HTTP
